<tv generator-info-name="youtube-live-epg" generator-info-url="https://github.com/dp247/YouTubeToM3U8">
  <channel id="ManaTolivelugu.yt">
    <display-name lang="en">ManaTolivelugu</display-name>
  </channel>
  <programme channel="ManaTolivelugu.yt" start="20240320130000 +0530" stop="20240320140000 +0530">
    <title lang="en">LIVE : Congress Ex Mp Mallu Ravi Press Meet || ManaTolivelugu</title>
    <desc lang="en">LIVE : Congress Ex Mp Mallu Ravi Press Meet || ManaTolivelugu</desc>
    <icon src="https://i.ytimg.com/vi/If_C9zI5Mtg/maxresdefault_live.jpg"/>
  </programme>
</tv>
